anbiliapi/__init__.py
anbiliapi/dynamic.py
anbiliapi/user.py
anbiliapi/utils/__init__.py
anbiliapi/utils/bilibili.py
anbiliapi/utils/credential.py
anbiliapi/utils/networkrequests.py
anbiliapi/video.py
anbiliapi-0.1a3.dist-info/WHEEL
anbiliapi-0.1a3.dist-info/METADATA
anbiliapi-0.1a3.dist-info/RECORD
