Metadata-Version: 2.1
Name: anbiliapi
Version: 0.1.a3
License: GPL-3.0
Author-email: alnthy <alnthy@qq.com>
Requires-Python: >=3.7
Requires-Dist: httpx>=0.23.1
Requires-Dist: pydantic>=1.10.2
